plotting_utils/__init__.py
plotting_utils/colors.py
plotting_utils/plotting_base.py
plotting_utils/utils.py
plotting_utils-0.1.5.dist-info/LICENSE
plotting_utils-0.1.5.dist-info/METADATA
plotting_utils-0.1.5.dist-info/WHEEL
plotting_utils-0.1.5.dist-info/top_level.txt
plotting_utils-0.1.5.dist-info/RECORD
