Metadata-Version: 2.2
Name: plotting_utils
Version: 0.1.5
Summary: Elegant wrappers around matplotlib and seaborn for scientific plotting
Home-page: https://github.com/andrecossa5/plotting_utils
Author: andrecossa5
Classifier: Programming Language :: Python :: 3
Classifier: License :: OSI Approved :: MIT License
Classifier: Operating System :: OS Independent
Requires-Python: >=3.6
License-File: LICENSE
Requires-Dist: seaborn
Requires-Dist: matplotlib
Requires-Dist: statannotations
Requires-Dist: textalloc
Requires-Dist: joblib
Requires-Dist: scikit-learn
Dynamic: author
Dynamic: classifier
Dynamic: description
Dynamic: description-content-type
Dynamic: home-page
Dynamic: requires-dist
Dynamic: requires-python
Dynamic: summary
